{
  "providing": {
    "python": [

    ]
  },
  "long_description": "",
  "replacing": {

  },
  "license": "Apache 2.0",
  "maintainer": "Opscode, Inc.",
  "attributes": {

  },
  "recommendations": {

  },
  "recipes": {
    "python": ""
  },
  "dependencies": {

  },
  "maintainer_email": "cookbooks@opscode.com",
  "suggestions": {

  },
  "platforms": {
    "debian": [

    ],
    "ubuntu": [

    ]
  },
  "description": "Installs python packages",
  "name": "python",
  "version": "0.7.0",
  "conflicting": {

  }
}